PyCommandsTool/__init__.py
PyCommandsTool/parser.py
PyCommandsTool/pycommandstool.py
PyCommandsTool-2.1.1.dist-info/LICENSE.md
PyCommandsTool-2.1.1.dist-info/METADATA
PyCommandsTool-2.1.1.dist-info/WHEEL
PyCommandsTool-2.1.1.dist-info/top_level.txt
PyCommandsTool-2.1.1.dist-info/RECORD
