Metadata-Version: 2.1
Name: PyCommandsTool
Version: 2.1.1
Summary: A simple and easy-to-use module that streamlines the whole user-input side of your script.
Author-email: Haven Selph <havenselph@gmail.com>
License: > MIT License
Project-URL: Documentation, https://github.com/HavenSelph/PyCommands/wiki/Documentation
Project-URL: Issues, https://github.com/HavenSelph/PyCommands/issues
Classifier: Development Status :: 5 - Production/Stable
Classifier: Programming Language :: Python :: 3
Classifier: License :: OSI Approved :: MIT License
Classifier: Operating System :: OS Independent
Requires-Python: >=3.5
License-File: LICENSE.md
